paroles_net.py
utils.py
models/__init__.py
models/song.py
paroles_net_wrapper-0.0.6.dist-info/licenses/LICENSE
paroles_net_wrapper-0.0.6.dist-info/METADATA
paroles_net_wrapper-0.0.6.dist-info/WHEEL
paroles_net_wrapper-0.0.6.dist-info/top_level.txt
paroles_net_wrapper-0.0.6.dist-info/RECORD
