Metadata-Version: 2.4
Name: paroles-net-wrapper
Version: 0.0.6
Summary: Ce projet permet de récupérer les paroles de chansons de paroles.net.
Home-page: https://github.com/Starland9/paroles-net-wrapper.git
Author: Starland9
Author-email: landrysimo99@gmail.com
License: MIT
License-File: LICENSE
Requires-Dist: beautifulsoup4
Requires-Dist: requests
Requires-Dist: selenium
Dynamic: author
Dynamic: author-email
Dynamic: description
Dynamic: description-content-type
Dynamic: home-page
Dynamic: license
Dynamic: license-file
Dynamic: requires-dist
Dynamic: summary
